hpc_tutorial/__init__.py
hpc_tutorial/__main__.py
hpc_tutorial/cli.py
hpc_tutorial/main.py
hpc_tutorial/py.typed
hpc_tutorial-1.0.0.dist-info/licenses/LICENSE
hpc_tutorial-1.0.0.dist-info/METADATA
hpc_tutorial-1.0.0.dist-info/WHEEL
hpc_tutorial-1.0.0.dist-info/entry_points.txt
hpc_tutorial-1.0.0.dist-info/top_level.txt
hpc_tutorial-1.0.0.dist-info/RECORD
