Metadata-Version: 2.4
Name: hpc-tutorial
Version: 1.0.0
Summary: Compare multiple distributed computation frameworks
Author-email: 34j <34j.95a2p@simplelogin.com>
License-Expression: MIT
Project-URL: Bug Tracker, https://github.com/ultrasphere-dev/hpc-tutorial/issues
Project-URL: Changelog, https://github.com/ultrasphere-dev/hpc-tutorial/blob/main/CHANGELOG.md
Project-URL: documentation, https://hpc-tutorial.readthedocs.io
Project-URL: repository, https://github.com/ultrasphere-dev/hpc-tutorial
Classifier: Development Status :: 2 - Pre-Alpha
Classifier: Intended Audience :: Developers
Classifier: Natural Language :: English
Classifier: Operating System :: OS Independent
Classifier: Programming Language :: Python :: 3.10
Classifier: Programming Language :: Python :: 3.11
Classifier: Programming Language :: Python :: 3.12
Classifier: Programming Language :: Python :: 3.13
Classifier: Programming Language :: Python :: 3.14
Classifier: Topic :: Software Development :: Libraries
Requires-Python: >=3.10
License-File: LICENSE
Requires-Dist: rich>=10
Requires-Dist: typer<1,>=0.15
Dynamic: license-file
